Museum_API_conversions.py
Museum_API_conversions-0.0.6.dist-info/METADATA
Museum_API_conversions-0.0.6.dist-info/WHEEL
Museum_API_conversions-0.0.6.dist-info/top_level.txt
Museum_API_conversions-0.0.6.dist-info/RECORD
